checksum_helper/__init__.py
checksum_helper/__main__.py
checksum_helper/checksum_helper.py
checksum_helper/py.typed
checksum_helper-0.2.6.dist-info/licenses/LICENSE.txt
checksum_helper-0.2.6.dist-info/METADATA
checksum_helper-0.2.6.dist-info/WHEEL
checksum_helper-0.2.6.dist-info/entry_points.txt
checksum_helper-0.2.6.dist-info/top_level.txt
checksum_helper-0.2.6.dist-info/RECORD
