Metadata-Version: 2.4
Name: checksum-helper
Version: 0.2.6
Summary: Helper tool for checksum file operations
Author-email: omgitsmoe <60219950+omgitsmoe@users.noreply.github.com>
License: MIT License
Project-URL: Homepage, https://github.com/omgitsmoe/checksum_helper
Project-URL: Bug Tracker, https://github.com/omgitsmoe/checksum_helper/issues
Keywords: script,checksum,verify,sha512,md5,sha256,backup,archival,bit-rot
Classifier: Programming Language :: Python :: 3
Classifier: License :: OSI Approved :: MIT License
Classifier: Operating System :: OS Independent
Requires-Python: >=3.6
License-File: LICENSE.txt
Provides-Extra: test
Requires-Dist: pytest<8,>=7.2; extra == "test"
Dynamic: license-file
